promptmask/__init__.py
promptmask/adapter/__init__.py
promptmask/adapter/openai.py
promptmask/config.py
promptmask/core.py
promptmask/promptmask.config.default.toml
promptmask/utils.py
promptmask/web/__init__.py
promptmask/web/gateway.py
promptmask/web/main.py
promptmask/web/models.py
promptmask/web/static/index.html
promptmask-0.1.1.dist-info/licenses/LICENSE
promptmask-0.1.1.dist-info/WHEEL
promptmask-0.1.1.dist-info/entry_points.txt
promptmask-0.1.1.dist-info/METADATA
promptmask-0.1.1.dist-info/RECORD
