Metadata-Version: 2.4
Name: promptmask
Version: 0.1.1
Summary: A local-first privacy layer for Large Language Models.
Author: cxumol
Author-email: cxumol <cxumol@gmail.com>
License-Expression: MIT
License-File: LICENSE
Classifier: Programming Language :: Python :: 3.8
Classifier: Programming Language :: Python :: 3.9
Classifier: Programming Language :: Python :: 3.10
Classifier: Programming Language :: Python :: 3.11
Classifier: License :: OSI Approved :: MIT License
Classifier: Operating System :: OS Independent
Classifier: Topic :: Software Development :: Libraries :: Python Modules
Classifier: Topic :: Software Development :: Libraries
Classifier: Topic :: Software Development
Requires-Dist: openai>=1.10
Requires-Dist: httpx>=0.25
Requires-Dist: tomli ; python_full_version < '3.11'
Requires-Dist: ruff ; extra == 'dev'
Requires-Dist: tqdm ; extra == 'dev'
Requires-Dist: icecream ; extra == 'dev'
Requires-Dist: pytest ; extra == 'dev'
Requires-Dist: pytest-asyncio ; extra == 'dev'
Requires-Dist: mkdocs ; extra == 'docs'
Requires-Dist: mkdocstrings[python]>=0.18 ; extra == 'docs'
Requires-Dist: brotli ; extra == 'web'
Requires-Dist: tomli-w ; extra == 'web'
Requires-Dist: httpx-sse>=0.4 ; extra == 'web'
Requires-Dist: fastapi>=0.100 ; extra == 'web'
Requires-Dist: uvicorn[standard]>=0.20 ; extra == 'web'
Requires-Python: >=3.8
Project-URL: Homepage, https://github.com/cxumol/promptmask
Project-URL: Issues, https://github.com/cxumol/promptmask/issues
Provides-Extra: dev
Provides-Extra: docs
Provides-Extra: web
